{"hostname": "cdms-gw", "DiskSpaceUtilization": {"lastRead": "Wed Sep 07 14:22:11 PDT 2022", "nmDiskSpaceChk": 2, "MaxDiskSpceChk%": 34.2, "MinDiskSpaceChk%": 18.2, "nmGtrThreshold": 0}, "ProcessorUtilization": {"lastRead": "Wed Sep 07 14:22:11 PDT 2022", "nmCPUs": 40, "MaxCPUutilized%": 0.0, "MinCPUutilized%": 0.0, "MeanCPUutilized%": 0.025}, "MemoryUtilization": {"lastRead": "Wed Sep 07 14:22:11 PDT 2022", "Memoryused%": 3.7, "MemTotinGB": 62.56, "SwapMemoryused%": 0.0, "SwapMemTotinGB": 3.7}}